topsis/__init__.py
topsis/topsis.py
topsisg-1.0.0.dist-info/METADATA
topsisg-1.0.0.dist-info/WHEEL
topsisg-1.0.0.dist-info/entry_points.txt
topsisg-1.0.0.dist-info/top_level.txt
topsisg-1.0.0.dist-info/RECORD
