Metadata-Version: 2.1
Name: topsisg
Version: 1.0.0
Summary: A Python package for the TOPSIS algorithm
Home-page: https://github.com/yourusername/topsis
Author: Sumit Garg
Author-email: your.email@example.com
Classifier: Programming Language :: Python :: 3
Classifier: License :: OSI Approved :: MIT License
Classifier: Operating System :: OS Independent
Requires-Python: >=3.6
Requires-Dist: numpy
